eventgateway/__init__.py
tests/__init__.py
tests/context.py
tests/test_egHappyPath.py
event_gateway_sdk-1.2.0.dist-info/LICENSE
event_gateway_sdk-1.2.0.dist-info/METADATA
event_gateway_sdk-1.2.0.dist-info/WHEEL
event_gateway_sdk-1.2.0.dist-info/top_level.txt
event_gateway_sdk-1.2.0.dist-info/RECORD
