Metadata-Version: 2.1
Name: event-gateway-sdk
Version: 1.2.0
Summary: Event Gateway Python SDK
Home-page: https://github.com/kalote/event-gateway-sdk
Author: Johann BICH
Author-email: johannbich@gmail.com
License: UNKNOWN
Platform: UNKNOWN
Classifier: Programming Language :: Python :: 3
Classifier: License :: OSI Approved :: MIT License
Classifier: Operating System :: OS Independent
Requires-Dist: requests
